mem.v
module ram # 
(parameter DATA_WIDTH = 64, ADDR_WIDTH = 16) //default is: 64b/word * (2^16)address) = 4Mb
(
clk         , // Clock Input
address     , // Address Input
d           , // Data input
q           , // Data output
cs          , // Chip Select
web           // Write Enable/Read Enable, low active
); 

localparam RAM_DEPTH = 1 << ADDR_WIDTH;

//--------------Input Ports----------------------- 
input clk;
input [ADDR_WIDTH-1:0] address;
input cs;
input web;

//--------------Inout Ports----------------------- 
input [DATA_WIDTH-1:0]  d;
output [DATA_WIDTH-1:0]  q;
reg [DATA_WIDTH-1:0]  data_out;

//--------------Internal variables---------------- 
reg [DATA_WIDTH-1:0] mem [0:RAM_DEPTH-1];

//--------------Core Function--------------------- 
// Tri-State Buffer control 
// output : When web = 1, oe = 1, cs = 1
assign q = (cs) ? data_out : 'bz; 

// Memory Write Block 
// Write Operation : When web = 0, cs = 1
always @ (posedge clk)
begin : MEM_WRITE
   if ( cs && ~web ) begin
       mem[address] = d;
   end
end

// Memory Read Block 
// Read Operation : When web = 1, oe = 1, cs = 1
always @ (address or cs or web)
begin : MEM_READ
    if (cs && web ) begin
         data_out = mem[address];
    end
end

endmodule

accelerator.v

module accelerator (
    clk, comp_enb, 
    mem_addr, mem_data, 
    mem_read_enb, mem_write_enb, 
    res_addr, res_data, 
    busyb, done
);

    input clk;
    input comp_enb;
    output reg [3:0] mem_addr;
    input [63:0] mem_data;
    output reg mem_read_enb;
    output reg mem_write_enb;
    output reg [3:0] res_addr;
    output reg [63:0] res_data;
    output reg busyb;
    output reg done;

    
    // Declare states
	parameter S_RST = 0, S_READ = 1, S_WORK = 2, S_DONE = 3;
	reg [1:0] state;
    reg [1:0] counter;
    reg [63:0] reg1, reg2;
	// Determine the next state synchronously, based on the
	// current state and the input
	always @ (posedge clk) begin
		if (comp_enb) begin
			state <= S_RST;
            res_addr <= 0;
            res_data <= 0;
            reg1 <= 0;
            reg2 <= 0;
            counter <= 0;
            mem_read_enb <= 0;
            mem_write_enb <= 1;
		end
		else begin
			case (state)
				S_RST: begin
                    if(~comp_enb)
                        state <= S_READ;
                end
				S_READ: begin
                    if(counter == 2'd0) begin
                        mem_addr <= 4'd0;
                        counter <= counter + 1;
                    end 
                    else if (counter == 2'd1) begin
                        reg1 <= mem_data;
                        mem_addr <= 4'd1;
                        counter <= counter + 1;
                    end
                    else if (counter == 2'd2) begin
                        reg2 <= mem_data;
                        counter <= 0;
                        state <= S_WORK;
                    end
                end
                S_WORK: begin
                    if(counter==0) begin
                        mem_write_enb <= 0;
                        res_addr = 4'd2;
                        res_data = reg1 + reg2;
                        counter <= counter + 1;
                    end
                    else begin
                        mem_write_enb <= 1;
                        counter <= 0;
                        state <= S_DONE;
                    end
                end
                default: begin //S_DONE
                    if(comp_enb)
                        state <= S_RST;
                end
			endcase
	    end
    end
	
	// Determine the output based only on the current state
	// and the input (do not wait for a clock edge).
	always @ (state)
	begin
		case (state)
			S_WORK: begin
                busyb <= 0;
                done <= 0;
            end
            S_DONE: begin
                busyb <= 0;
                done <= 1;
            end
            default: begin //S_RST
                busyb <= 1;
                done <= 0;
            end
		endcase
	end

endmodule

testbench_top.v

`timescale 1ns/1ns
`include "mem.v"
`include "accelerator.v"
`define T 2 // define macro for clock period

module testbench_top;

integer i, file1;
reg clk = 0;
always #(`T/2) clk = ~clk;
reg comp_enb;

wire [3:0] mem_addr;
wire [63:0] mem_data;
wire mem_read_enb;
wire mem_write_enb;
wire [3:0] res_addr;
wire [63:0] res_data;
wire busyb, done;
initial
begin
    $dumpfile("wave.vcd");
    $dumpvars(0);
end

accelerator u_accelerator (
 .clk           (clk)
,.comp_enb      (comp_enb)
,.mem_addr      (mem_addr)
,.mem_data      (mem_data)
,.mem_read_enb  (mem_read_enb)
,.mem_write_enb (mem_write_enb)
,.res_addr      (res_addr)
,.res_data      (res_data)
,.busyb         (busyb)
,.done          (done)
);

ram #(.DATA_WIDTH(64), .ADDR_WIDTH(4)) u_input_mem (
 .clk       (clk)
,.web       (~mem_read_enb)
,.address   (mem_addr)
,.d         ()
,.q         (mem_data)
,.cs        (1'b1)
);

ram #(.DATA_WIDTH(64), .ADDR_WIDTH(4)) u_res_mem (
 .clk       (clk)
,.web       (mem_write_enb)
,.address   (res_addr)
,.d         (res_data)
,.q         (),
.cs         (1'b1)
);

// %%%%%%%%%%%%%%%%%%%%%%%%%%%%%%%%%%%%%%%%%%%%%%%%%%%
initial begin
    // start simulation
    $readmemh("input_mem.csv", u_input_mem.mem);
    comp_enb = 1;
    #(`T) comp_enb = 0;
    
    // finishing simulation
    #(10*`T) begin
        // readout result_memory content to "result_mem.csv"
        file1=$fopen("result_mem.csv","w");
        for(i=0;i<(1<<4);i++)
            $fwrite( file1 , "%8h\n" , u_res_mem.mem[i]);
        $fclose(file1);
        $finish; 
    end
end
endmodule

wave.vcd
$date
	Thu May 30 00:02:00 2024
$end
$version
	Icarus Verilog
$end
$timescale
	1ns
$end
$scope module testbench_top $end
$var wire 64 ! res_data [63:0] $end
$var wire 4 " res_addr [3:0] $end
$var wire 1 # mem_write_enb $end
$var wire 1 $ mem_read_enb $end
$var wire 64 % mem_data [63:0] $end
$var wire 4 & mem_addr [3:0] $end
$var wire 1 ' done $end
$var wire 1 ( busyb $end
$var reg 1 ) clk $end
$var reg 1 * comp_enb $end
$var integer 32 + file1 [31:0] $end
$var integer 32 , i [31:0] $end
$scope module u_accelerator $end
$var wire 1 ) clk $end
$var wire 1 * comp_enb $end
$var wire 64 - mem_data [63:0] $end
$var parameter 32 . S_DONE $end
$var parameter 32 / S_READ $end
$var parameter 32 0 S_RST $end
$var parameter 32 1 S_WORK $end
$var reg 1 ( busyb $end
$var reg 2 2 counter [1:0] $end
$var reg 1 ' done $end
$var reg 4 3 mem_addr [3:0] $end
$var reg 1 $ mem_read_enb $end
$var reg 1 # mem_write_enb $end
$var reg 64 4 reg1 [63:0] $end
$var reg 64 5 reg2 [63:0] $end
$var reg 4 6 res_addr [3:0] $end
$var reg 64 7 res_data [63:0] $end
$var reg 2 8 state [1:0] $end
$upscope $end
$scope module u_input_mem $end
$var wire 4 9 address [3:0] $end
$var wire 1 ) clk $end
$var wire 1 : cs $end
$var wire 64 ; d [63:0] $end
$var wire 64 < q [63:0] $end
$var wire 1 = web $end
$var parameter 32 > ADDR_WIDTH $end
$var parameter 32 ? DATA_WIDTH $end
$var parameter 36 @ RAM_DEPTH $end
$var reg 64 A data_out [63:0] $end
$scope begin MEM_READ $end
$upscope $end
$scope begin MEM_WRITE $end
$upscope $end
$upscope $end
$scope module u_res_mem $end
$var wire 4 B address [3:0] $end
$var wire 1 ) clk $end
$var wire 1 C cs $end
$var wire 64 D d [63:0] $end
$var wire 64 E q [63:0] $end
$var wire 1 # web $end
$var parameter 32 F ADDR_WIDTH $end
$var parameter 32 G DATA_WIDTH $end
$var parameter 36 H RAM_DEPTH $end
$var reg 64 I data_out [63:0] $end
$scope begin MEM_READ $end
$upscope $end
$scope begin MEM_WRITE $end
$upscope $end
$upscope $end
$upscope $end
$enddefinitions $end
$comment Show the parameter values. $end
$dumpall
b10000 H
b1000000 G
b100 F
b10000 @
b1000000 ?
b100 >
b10 1
b0 0
b1 /
b11 .
$end
#0
$dumpvars
bx I
bx E
bx D
1C
bx B
bx A
x=
bx <
bz ;
1:
bx 9
bx 8
bx 7
bx 6
bx 5
bx 4
bx 3
bx 2
bx -
bx ,
bx +
1*
0)
x(
x'
bx &
bx %
x$
x#
bx "
bx !
$end
#1
0'
1(
1=
1#
0$
b0 2
b0 5
b0 4
b0 !
b0 7
b0 D
b0 "
b0 6
b0 B
b0 8
1)
#2
0)
0*
#3
b1 8
1)
#4
0)
#5
b1000100010001 %
b1000100010001 -
b1000100010001 <
b1000100010001 A
b1 2
b0 &
b0 3
b0 9
1)
#6
0)
#7
b10001000100010 %
b10001000100010 -
b10001000100010 <
b10001000100010 A
b10 2
b1 &
b1 3
b1 9
b1000100010001 4
1)
#8
0)
#9
0(
b10 8
b0 2
b10001000100010 5
1)
#10
0)
#11
b1 2
0#
b11001100110011 !
b11001100110011 7
b11001100110011 D
b10 "
b10 6
b10 B
1)
#12
0)
#13
1'
b11001100110011 E
b11001100110011 I
b11 8
b0 2
1#
1)
#14
0)
#15
1)
#16
0)
#17
1)
#18
0)
#19
1)
#20
0)
#21
1)
#22
0)
b10000 ,
b10000000000000000000000000000011 +
